{"1":{"id":"1","name":"Igiene","duration":"60","buffertime_before":"0","buffertime_after":"0","hide_duration":"0","description":" booking any service using voice natural language using many channels ","is_public":"1","is_active":"1","position":"1","file_id":null,"seo_url":"sermovox","is_recurring":"0","picture":null,"picture_sub_path":null,"is_visible":"1","picture_path":null,"unit_map":{"3":null,"4":null},"providers":[3,4],"classes_plugin_info":{"unit_group_binded_in_class":null,"unit_groups_binded_in_classes":[]}},"2":{"id":"2","name":"Controllo e vaccinazioni","duration":"60","buffertime_before":"0","buffertime_after":"0","hide_duration":"0","description":null,"is_public":"1","is_active":"1","position":"5","file_id":null,"seo_url":null,"is_recurring":"0","picture":null,"picture_sub_path":null,"is_visible":"1","picture_path":null,"unit_map":{"1":null,"2":null},"providers":[1,2],"classes_plugin_info":{"unit_group_binded_in_class":null,"unit_groups_binded_in_classes":[]}},"3":{"id":"3","name":"Visita  per rinnovo patente","duration":"60","buffertime_before":"0","buffertime_after":"0","hide_duration":"0","description":null,"is_public":"1","is_active":"1","position":"8","file_id":null,"seo_url":null,"is_recurring":"0","picture":null,"picture_sub_path":null,"is_visible":"1","picture_path":null,"classes_plugin_info":{"unit_group_binded_in_class":null,"unit_groups_binded_in_classes":[]}}}
